SystemVerilog/MNPU2-hdl/MNPU2_stack.sv
`timescale 1ps/1ps

module stack (
    input clk, reset, toggle_exec_in,
    input [5:0] pc_in,
    input [7:0] instruction_in, data_in, page_in, 
    
    output logic [5:0] pc_out,
    output logic [7:0] page_out, data_out
);

localparam DSTACK_SIZE = 8;
localparam CSTACK_SIZE = 8;

logic [3:0] dsp, csp;
logic [7:0] dstack [DSTACK_SIZE];
logic [13:0] cstack [CSTACK_SIZE];

assign data_out = (dsp > 0) ? dstack[dsp - 1] : 0;
assign {page_out, pc_out} = (csp > 0) ? cstack[csp - 1] : 0;

always_ff @(posedge clk) begin
    if (reset) begin
        dsp <= 0;
        csp <= 0;
        for (int i = 0; i < DSTACK_SIZE; i = i + 1) begin
            dstack[i] <= 0;
            cstack[i] <= 0;
        end
    end
    else begin
        if (toggle_exec_in) begin
            case (instruction_in[7:3])
                17: begin // CALL
                    if (csp < CSTACK_SIZE) begin
                        cstack[csp] <= {page_in, pc_in+2'd2};
                        csp <= csp + 1;
                    end
                end
                18: begin // RET
                    if (csp > 0) begin
                        csp <= csp - 1;
                        cstack[csp - 1] <= 0;
                    end 
                end
                22: begin // PUSH
                    if (dsp < DSTACK_SIZE) begin
                        dstack[dsp] <= data_in;
                        dsp <= dsp + 1;
                    end
                end
                23: begin // POP
                    if (dsp > 0) begin
                        dsp <= dsp - 1;
                        dstack[dsp - 1] <= 0;
                    end 
                end
            endcase
        end
    end
end

endmodule

SystemVerilog/MNPU2-hdl/MNPU2_ram.sv
`timescale 1ps/1ps

module ram (
    input clk, reset, toggle_exec_in,
    input [7:0] instruction_in, acc_in, reg_in,
    
    output logic [7:0] ram_out
);

logic [7:0] ram [0:255];
logic [7:0] poi;

assign ram_out = ram[poi];

always_ff @(posedge clk) begin
    if (reset) begin
        poi <= 0;
        for (int i = 0; i < 256; i = i + 1) begin
            ram[i] <= 0;
        end
    end
    else begin
        if (toggle_exec_in) begin
            case (instruction_in[7:3])
                24: begin // POI
                    poi <= reg_in;
                end
                25: begin // MST
                    ram[poi] <= acc_in;
                end
            endcase
        end
    end
end

endmodule

SystemVerilog/MNPU2-hdl/MNPU2_io.sv
`timescale 1ps/1ps

module io (
    input clk, reset, toggle_exec_in,
    input [7:0] acc_in, instruction_in,

    input in_confirm,
    input [7:0] in [0:7],

    output [7:0] input_out,
    output logic out_info [0:7],
    output logic [7:0] out [0:7]
);

assign input_out = in[instruction_in[2:0]]; // there is no halt on input (todo), also there is no halt in general for now

always_ff @(posedge clk) begin
    if (reset) begin
        for (int i = 0; i < 8; i = i + 1) begin
            out[i] <= 0;
            out_info[i] <= 0;
        end
    end
    else begin
        for (int i = 0; i < 8; i = i + 1) begin
            out_info[i] <= 0;
        end
        if (toggle_exec_in) begin
            if (instruction_in[7:3] == 20) begin // OUT
                out[instruction_in[2:0]] <= acc_in;
                out_info[instruction_in[2:0]] <= 1;
            end
        end
    end
end

endmodule

SystemVerilog/MNPU2-hdl/MNPU2_regs.sv
`timescale 1ps/1ps

module regs (
    input clk, reset, toggle_exec_in,
    input [7:0] instruction_in, data_in,
    
    output logic [7:0] reg_out
);
    logic imm, writeback;

    logic [2:0] address, address_buffer;
    assign address = instruction_in[2:0];

    logic [7:0] register [1:7];

    always_comb begin
        if ((address == address_buffer) && writeback) reg_out = data_in;
        else if (address == 0) reg_out = 0;
        else reg_out = register[address];
    end

    always_ff @(posedge clk) begin
        if (reset) begin
            for (int i = 1; i < 8; i = i + 1) register[i] <= 0;
            address_buffer <= 0;
            imm <= 0;
            writeback <= 0;
        end
        else begin
            writeback <= 0;
            imm <= 0;
            address_buffer <= address;
            if (toggle_exec_in) begin
                if ((address_buffer != 0) && writeback) register[address_buffer] <= data_in;
                case (instruction_in[7:3])
                    0, 6, 7, 8, 9, 13: begin //reg writeback
                        writeback <= 1;
                    end
                endcase
                if (instruction_in[7:3] == 14) imm <= 1;
            end
            if (imm) begin
                if (address_buffer != 0) register[address_buffer] <= data_in;
            end
        end
    end

endmodule

SystemVerilog/MNPU2-hdl/MNPU2_alu.sv
`timescale 1ps/1ps

module alu(
    input clk, reset, toggle_exec_in,
    input [7:0] instruction_in, reg_in, ram_in, dstack_in, input_in,
    
    output logic [7:0] sum_out, acc_out,
    output logic cout_out, zero_out, msb_lsb_out
);
    wire [4:0] instr;
    assign instr = instruction_in[7:3];

    logic imm, ima, cout, zero, msb_lsb;
    logic [7:0] sum, sum_buffer;

    assign zero = ~|sum;
    assign msb_lsb = sum&8'b0000_0001; // LSB

    always_comb begin
        sum = 0;
        cout = 0;
        if (toggle_exec_in) begin
            case (instr)
                0: begin //RST
                    sum = acc_out;
                end
                1: begin //RST
                    sum = reg_in;
                end
                2: begin // ADD
                    {cout, sum} = acc_out + reg_in;
                end
                3: begin // BSUB
                    {cout, sum} = {1'b0, ~acc_out} + {1'b0, reg_in} + 1'b1;
                end
                4: begin // SUB
                    {cout, sum} = {1'b0, acc_out} + {1'b0, ~reg_in} + 1'b1;
                end
                5: begin // CMP
                    {cout, sum} = {1'b0, acc_out} + {1'b0, ~reg_in} + 1'b1;
                end
                6: begin // INC
                    {cout, sum} = reg_in + 1'b1;
                end
                7: begin // DEC
                    {cout, sum} = reg_in + 8'hff;
                end
                8: begin // RSH
                    {sum, cout} = {1'b0, reg_in};
                end
                9: begin // LSH
                    {cout, sum} = {reg_in, 1'b0};
                end
                10: begin // XOR
                    {cout, sum} = {1'b1, acc_out ^ reg_in}; //cout from bitwise operations might be wrong, but its useless anyway
                end
                11: begin // OR
                    {cout, sum} = {1'b0, acc_out | reg_in};
                end
                12: begin // AND
                    {cout, sum} = {1'b1, acc_out & reg_in};
                end
                13: begin // NOT
                    {cout, sum} = {1'b0, ~reg_in};
                end
                19: begin // IN
                    {cout, sum} = {1'b0, input_in};
                end
                20: begin // OUT
                    sum = acc_out;
                end
                23: begin // POP
                    {cout, sum} = {1'b0, dstack_in};
                end
                26: begin // MLD
                    {cout, sum} = {1'b0, ram_in};
                end
                27: begin // ADDC
                    {cout, sum} = acc_out + reg_in + cout_out;
                end
                28: begin //SUBC
                    {cout, sum} = {1'b0, acc_out} + {1'b0, ~reg_in} + cout_out;
                end
                29: begin // NEG
                    {cout, sum} = ~reg_in + 1'b1;
                end
                30: begin // NEGA
                    {cout, sum} = ~acc_out + 1'b1;
                end
            endcase
        end
        if (imm || ima) sum_out = instruction_in;
        else sum_out = sum_buffer;
    end
     
    always_ff @(posedge clk) begin
        imm <= 0;
        ima <= 0;
        if (reset) begin
            acc_out <= 0;
            sum_buffer <= 0;
            cout_out <= 0;
            zero_out <= 0;
            msb_lsb_out <= 0;
        end
        else begin
            sum_buffer <= sum;
            if (toggle_exec_in) begin
                case (instr)
                    1, 2, 3, 4, 10, 11, 12, 19, 23, 26, 27, 28, 30: // acc writeback
                        acc_out <= sum;
                endcase
                case (instr)
                    2, 3, 4, 5, 6, 7, 8, 9, 10, 11, 12, 13, 19, 23, 26, 27, 28, 29, 30: begin // flag update
                        cout_out <= cout;
                        zero_out <= zero;
                        msb_lsb_out <= msb_lsb;
                    end
                endcase

                if (instr == 14) imm <= 1;
                if (instr == 15) ima <= 1;
            end
            if (ima) acc_out <= sum_out;
        end
    end

endmodule

SystemVerilog/MNPU2-hdl/MNPU2_exe_control.sv
`timescale 1ps/1ps

module exe_control (
    input clk, reset, flush_in,
    input [4:0] instruction_in,
    
    output logic toggle_exec_out, running
);
    logic [1:0] immediate_count;

    assign toggle_exec_out = ~|immediate_count & !flush_in;

    always_ff @(posedge clk) begin
        if (reset) begin
            immediate_count <= 0;
            running <= 1;
        end
        else begin
            immediate_count <= immediate_count >> 1;
            if (toggle_exec_out) begin
                case (instruction_in)
                    14, 15, 21: immediate_count <= 1;
                    16, 17: immediate_count <= 2;
                    31: running <= 0;
                endcase
            end
        end
    end

endmodule

SystemVerilog/MNPU2-hdl/MNPU2_rom.sv
`timescale 1ps/1ps

module rom (
    input clk,
    input [5:0] pc_in,
    input [7:0] page_in,
    output logic [7:0] instruction_out
);

    logic [7:0] rom [0:16383];

    initial begin
        $readmemb("program.bin", rom);
    end

    always_ff @(posedge clk) begin
        instruction_out <= rom[{page_in, pc_in}];
    end

endmodule

SystemVerilog/MNPU2-hdl/MNPU2_pc.sv
`timescale 1ps/1ps

module pc (
    input clk, reset, toggle_exec_in, zero_in, cout_in, msb_lsb_in,
    input [5:0] pc_in,
    input [7:0] instruction_in, page_in,

    output logic flush_out,
    output logic [5:0] pc_out,
    output logic [7:0] page_out
);

logic brc, cond;
logic [1:0] swp;
logic [7:0] swp_tmp;

always_ff @(posedge clk) begin
    brc <= 0;
    swp <= swp >> 1;
    if (reset) begin
        pc_out <= 0;
        page_out <= 0;
        swp <= 0;
        swp_tmp <= 0;
        flush_out <= 0;
    end
    else begin
        flush_out <= 0;
        
        pc_out <= pc_out + 1;
        case (instruction_in[2:0])
            0: cond <= 1; // TRUE
            1: cond <= !zero_in; // NEQ, NZERO
            2: cond <= zero_in; // EQ, ZERO
            3: cond <= !cout_in; // LT, NCARRY
            4: cond <= !cout_in || zero_in; // LEQ
            5: cond <= cout_in && !zero_in; // GT
            6: cond <= cout_in; // GEQ, CARRY
            7: cond <= msb_lsb_in; // MSB/LSB
        endcase
        if (toggle_exec_in) begin
            case (instruction_in[7:3])
                21: brc <= 1; // BRC
                16, 17: swp <= 2; // SWP/CALL
                18: {page_out, pc_out} <= {page_in, pc_in}; // RET
            endcase
        end
        if (brc && cond) begin
            pc_out <= instruction_in[5:0];
            flush_out <= 1;
        end
        if (swp[1]) swp_tmp <= instruction_in;
        if (swp[0]) begin
            page_out <= swp_tmp;
            pc_out <= instruction_in[5:0];
            flush_out <= 1;
        end
    end
end

endmodule

SystemVerilog/MNPU2-hdl/MNPU2.sv
`timescale 1ps/1ps

module MNPU2 (
    input clk, reset,
    output logic running,

    input in_confirm,
    input [7:0] in [0:7],

    output logic out_info [0:7],
    output logic [7:0] out [0:7]
);
    logic toggle_exec, flush, zero, cout, msb_lsb;
    logic [5:0] pc, cstack_pc;
    logic [7:0] page, instruction, sum, register, acc, ram, dstack, cstack_page, io;

    pc pc_name (.clk(clk), .reset(reset), .toggle_exec_in(toggle_exec), .zero_in(zero), .cout_in(cout), .msb_lsb_in(msb_lsb), .instruction_in(instruction), .flush_out(flush), .pc_out(pc), .page_out(page), .pc_in(cstack_pc), .page_in(cstack_page));
    rom rom_name (.clk(clk), .pc_in(pc), .page_in(page), .instruction_out(instruction));
    exe_control exe_name (.clk(clk), .reset(reset), .flush_in(flush), .instruction_in(instruction[7:3]), .toggle_exec_out(toggle_exec), .running(running));
    alu alu_name (.clk(clk), .reset(reset), .toggle_exec_in(toggle_exec), .instruction_in(instruction), .reg_in(register), .sum_out(sum), .acc_out(acc), .cout_out(cout), .zero_out(zero), .msb_lsb_out(msb_lsb), .ram_in(ram), .dstack_in(dstack), .input_in(io));
    regs regs_name (.clk(clk), .reset(reset), .toggle_exec_in(toggle_exec), .instruction_in(instruction), .data_in(sum), .reg_out(register));
    io io_name (.clk(clk), .reset(reset), .toggle_exec_in(toggle_exec), .instruction_in(instruction), .acc_in(acc), .input_out(io), .in_confirm(in_confirm), .in(in), .out_info(out_info), .out(out));
    ram ram_name (.clk(clk), .reset(reset), .toggle_exec_in(toggle_exec), .instruction_in(instruction), .acc_in(acc), .reg_in(register), .ram_out(ram));
    stack stack_name (.clk(clk), .reset(reset), .toggle_exec_in(toggle_exec), .pc_in(pc), .instruction_in(instruction), .data_in(acc), .page_in(page), .data_out(dstack), .pc_out(cstack_pc), .page_out(cstack_page));

endmodule

SystemVerilog/MNPU2-hdl/MNPU2_tb.sv
`timescale 1ps/1ps

module MNPU2_tb;
    logic clk, reset, running;

    MNPU2 dut (.clk(clk), .reset(reset), .running(running));

    initial begin
        $dumpfile("MNPU2.vcd");
        $dumpvars(0, MNPU2_tb);
        // for (int i = 0; i < 16; i = i + 1) $dumpvars(0, dut.rom_name.mem[i]);
        $dumpvars(0, dut.regs_name.register[1]);
        $dumpvars(0, dut.regs_name.register[2]);
        $dumpvars(0, dut.regs_name.register[3]);
        $dumpvars(0, dut.regs_name.register[4]);
        $dumpvars(0, dut.regs_name.register[5]);
        $dumpvars(0, dut.regs_name.register[6]);
        $dumpvars(0, dut.regs_name.register[7]);

        $dumpvars(0, dut.io_name.out[0]);

        $dumpvars(0, dut.ram_name.ram[0]);
        $dumpvars(0, dut.ram_name.ram[1]);
        $dumpvars(0, dut.ram_name.ram[2]);
        $dumpvars(0, dut.ram_name.ram[3]);
        $dumpvars(0, dut.ram_name.ram[4]);
        $dumpvars(0, dut.ram_name.ram[5]);
        $dumpvars(0, dut.ram_name.ram[6]);
        $dumpvars(0, dut.ram_name.ram[7]);

        $dumpvars(0, dut.stack_name.dstack[0]);
        $dumpvars(0, dut.stack_name.dstack[1]);
        $dumpvars(0, dut.stack_name.dstack[2]);
        $dumpvars(0, dut.stack_name.dstack[3]);
        $dumpvars(0, dut.stack_name.dstack[4]);
        $dumpvars(0, dut.stack_name.dstack[5]);
        $dumpvars(0, dut.stack_name.dstack[6]);
        $dumpvars(0, dut.stack_name.dstack[7]);

        $dumpvars(0, dut.stack_name.cstack[0]);
        $dumpvars(0, dut.stack_name.cstack[1]);
        $dumpvars(0, dut.stack_name.cstack[2]);
        $dumpvars(0, dut.stack_name.cstack[3]);
        $dumpvars(0, dut.stack_name.cstack[4]);
        $dumpvars(0, dut.stack_name.cstack[5]);
        $dumpvars(0, dut.stack_name.cstack[6]);
        $dumpvars(0, dut.stack_name.cstack[7]);
    end

    initial begin
        reset = 1; #5;
        reset = 0; #5;
        #20000;
        $finish;
    end

    initial begin
        clk = 1;
        forever #5 clk = ~clk;
    end

    always @(negedge running) $finish;

endmodule

SystemVerilog/MNPU2-hdl/MNPU2.vcd
$date
	Sun Oct 04 18:24:25 2026
$end
$version
	Icarus Verilog
$end
$timescale
	1ps
$end
$scope module MNPU2_tb $end
$var wire 1 ! running $end
$var reg 1 " clk $end
$var reg 1 # reset $end
$scope module dut $end
$var wire 1 " clk $end
$var wire 1 $ in_confirm $end
$var wire 1 # reset $end
$var wire 1 % zero $end
$var wire 1 & toggle_exec $end
$var wire 8 ' sum [7:0] $end
$var wire 1 ! running $end
$var wire 8 ( register [7:0] $end
$var wire 8 ) ram [7:0] $end
$var wire 6 * pc [5:0] $end
$var wire 8 + page [7:0] $end
$var wire 1 , msb_lsb $end
$var wire 8 - io [7:0] $end
$var wire 8 . instruction [7:0] $end
$var wire 1 / flush $end
$var wire 8 0 dstack [7:0] $end
$var wire 6 1 cstack_pc [5:0] $end
$var wire 8 2 cstack_page [7:0] $end
$var wire 1 3 cout $end
$var wire 8 4 acc [7:0] $end
$scope module alu_name $end
$var wire 1 " clk $end
$var wire 1 # reset $end
$var wire 1 5 zero $end
$var wire 1 & toggle_exec_in $end
$var wire 8 6 reg_in [7:0] $end
$var wire 8 7 ram_in [7:0] $end
$var wire 1 8 msb_lsb $end
$var wire 8 9 instruction_in [7:0] $end
$var wire 5 : instr [4:0] $end
$var wire 8 ; input_in [7:0] $end
$var wire 8 < dstack_in [7:0] $end
$var reg 8 = acc_out [7:0] $end
$var reg 1 > cout $end
$var reg 1 3 cout_out $end
$var reg 1 ? ima $end
$var reg 1 @ imm $end
$var reg 1 , msb_lsb_out $end
$var reg 8 A sum [7:0] $end
$var reg 8 B sum_buffer [7:0] $end
$var reg 8 C sum_out [7:0] $end
$var reg 1 % zero_out $end
$upscope $end
$scope module exe_name $end
$var wire 1 " clk $end
$var wire 5 D instruction_in [4:0] $end
$var wire 1 # reset $end
$var wire 1 & toggle_exec_out $end
$var wire 1 / flush_in $end
$var reg 2 E immediate_count [1:0] $end
$var reg 1 ! running $end
$upscope $end
$scope module io_name $end
$var wire 8 F acc_in [7:0] $end
$var wire 1 " clk $end
$var wire 1 $ in_confirm $end
$var wire 8 G input_out [7:0] $end
$var wire 1 # reset $end
$var wire 1 & toggle_exec_in $end
$var wire 8 H instruction_in [7:0] $end
$scope begin $ivl_for_loop0 $end
$var integer 32 I i [31:0] $end
$upscope $end
$scope begin $ivl_for_loop1 $end
$var integer 32 J i [31:0] $end
$upscope $end
$upscope $end
$scope module pc_name $end
$var wire 1 " clk $end
$var wire 1 3 cout_in $end
$var wire 1 , msb_lsb_in $end
$var wire 1 # reset $end
$var wire 1 & toggle_exec_in $end
$var wire 1 % zero_in $end
$var wire 6 K pc_in [5:0] $end
$var wire 8 L page_in [7:0] $end
$var wire 8 M instruction_in [7:0] $end
$var reg 1 N brc $end
$var reg 1 O cond $end
$var reg 1 / flush_out $end
$var reg 8 P page_out [7:0] $end
$var reg 6 Q pc_out [5:0] $end
$var reg 2 R swp [1:0] $end
$var reg 8 S swp_tmp [7:0] $end
$upscope $end
$scope module ram_name $end
$var wire 8 T acc_in [7:0] $end
$var wire 1 " clk $end
$var wire 8 U ram_out [7:0] $end
$var wire 1 # reset $end
$var wire 1 & toggle_exec_in $end
$var wire 8 V reg_in [7:0] $end
$var wire 8 W instruction_in [7:0] $end
$var reg 8 X poi [7:0] $end
$scope begin $ivl_for_loop2 $end
$var integer 32 Y i [31:0] $end
$upscope $end
$upscope $end
$scope module regs_name $end
$var wire 1 " clk $end
$var wire 8 Z data_in [7:0] $end
$var wire 1 # reset $end
$var wire 1 & toggle_exec_in $end
$var wire 8 [ instruction_in [7:0] $end
$var wire 3 \ address [2:0] $end
$var reg 3 ] address_buffer [2:0] $end
$var reg 1 ^ imm $end
$var reg 8 _ reg_out [7:0] $end
$var reg 1 ` writeback $end
$scope begin $ivl_for_loop3 $end
$var integer 32 a i [31:0] $end
$upscope $end
$upscope $end
$scope module rom_name $end
$var wire 1 " clk $end
$var wire 8 b page_in [7:0] $end
$var wire 6 c pc_in [5:0] $end
$var reg 8 d instruction_out [7:0] $end
$upscope $end
$scope module stack_name $end
$var wire 1 " clk $end
$var wire 8 e data_in [7:0] $end
$var wire 8 f instruction_in [7:0] $end
$var wire 8 g page_in [7:0] $end
$var wire 6 h pc_in [5:0] $end
$var wire 1 # reset $end
$var wire 1 & toggle_exec_in $end
$var wire 6 i pc_out [5:0] $end
$var wire 8 j page_out [7:0] $end
$var wire 8 k data_out [7:0] $end
$var parameter 32 l CSTACK_SIZE $end
$var parameter 32 m DSTACK_SIZE $end
$var reg 4 n csp [3:0] $end
$var reg 4 o dsp [3:0] $end
$scope begin $ivl_for_loop4 $end
$var integer 32 p i [31:0] $end
$upscope $end
$upscope $end
$upscope $end
$upscope $end
$scope module MNPU2_tb $end
$scope module dut $end
$scope module regs_name $end
$var reg 8 q \register[1] [7:0] $end
$upscope $end
$upscope $end
$upscope $end
$scope module MNPU2_tb $end
$scope module dut $end
$scope module regs_name $end
$var reg 8 r \register[2] [7:0] $end
$upscope $end
$upscope $end
$upscope $end
$scope module MNPU2_tb $end
$scope module dut $end
$scope module regs_name $end
$var reg 8 s \register[3] [7:0] $end
$upscope $end
$upscope $end
$upscope $end
$scope module MNPU2_tb $end
$scope module dut $end
$scope module regs_name $end
$var reg 8 t \register[4] [7:0] $end
$upscope $end
$upscope $end
$upscope $end
$scope module MNPU2_tb $end
$scope module dut $end
$scope module regs_name $end
$var reg 8 u \register[5] [7:0] $end
$upscope $end
$upscope $end
$upscope $end
$scope module MNPU2_tb $end
$scope module dut $end
$scope module regs_name $end
$var reg 8 v \register[6] [7:0] $end
$upscope $end
$upscope $end
$upscope $end
$scope module MNPU2_tb $end
$scope module dut $end
$scope module regs_name $end
$var reg 8 w \register[7] [7:0] $end
$upscope $end
$upscope $end
$upscope $end
$scope module MNPU2_tb $end
$scope module dut $end
$scope module io_name $end
$var reg 8 x \out[0] [7:0] $end
$upscope $end
$upscope $end
$upscope $end
$scope module MNPU2_tb $end
$scope module dut $end
$scope module ram_name $end
$var reg 8 y \ram[0] [7:0] $end
$upscope $end
$upscope $end
$upscope $end
$scope module MNPU2_tb $end
$scope module dut $end
$scope module ram_name $end
$var reg 8 z \ram[1] [7:0] $end
$upscope $end
$upscope $end
$upscope $end
$scope module MNPU2_tb $end
$scope module dut $end
$scope module ram_name $end
$var reg 8 { \ram[2] [7:0] $end
$upscope $end
$upscope $end
$upscope $end
$scope module MNPU2_tb $end
$scope module dut $end
$scope module ram_name $end
$var reg 8 | \ram[3] [7:0] $end
$upscope $end
$upscope $end
$upscope $end
$scope module MNPU2_tb $end
$scope module dut $end
$scope module ram_name $end
$var reg 8 } \ram[4] [7:0] $end
$upscope $end
$upscope $end
$upscope $end
$scope module MNPU2_tb $end
$scope module dut $end
$scope module ram_name $end
$var reg 8 ~ \ram[5] [7:0] $end
$upscope $end
$upscope $end
$upscope $end
$scope module MNPU2_tb $end
$scope module dut $end
$scope module ram_name $end
$var reg 8 !" \ram[6] [7:0] $end
$upscope $end
$upscope $end
$upscope $end
$scope module MNPU2_tb $end
$scope module dut $end
$scope module ram_name $end
$var reg 8 "" \ram[7] [7:0] $end
$upscope $end
$upscope $end
$upscope $end
$scope module MNPU2_tb $end
$scope module dut $end
$scope module stack_name $end
$var reg 8 #" \dstack[0] [7:0] $end
$upscope $end
$upscope $end
$upscope $end
$scope module MNPU2_tb $end
$scope module dut $end
$scope module stack_name $end
$var reg 8 $" \dstack[1] [7:0] $end
$upscope $end
$upscope $end
$upscope $end
$scope module MNPU2_tb $end
$scope module dut $end
$scope module stack_name $end
$var reg 8 %" \dstack[2] [7:0] $end
$upscope $end
$upscope $end
$upscope $end
$scope module MNPU2_tb $end
$scope module dut $end
$scope module stack_name $end
$var reg 8 &" \dstack[3] [7:0] $end
$upscope $end
$upscope $end
$upscope $end
$scope module MNPU2_tb $end
$scope module dut $end
$scope module stack_name $end
$var reg 8 '" \dstack[4] [7:0] $end
$upscope $end
$upscope $end
$upscope $end
$scope module MNPU2_tb $end
$scope module dut $end
$scope module stack_name $end
$var reg 8 (" \dstack[5] [7:0] $end
$upscope $end
$upscope $end
$upscope $end
$scope module MNPU2_tb $end
$scope module dut $end
$scope module stack_name $end
$var reg 8 )" \dstack[6] [7:0] $end
$upscope $end
$upscope $end
$upscope $end
$scope module MNPU2_tb $end
$scope module dut $end
$scope module stack_name $end
$var reg 8 *" \dstack[7] [7:0] $end
$upscope $end
$upscope $end
$upscope $end
$scope module MNPU2_tb $end
$scope module dut $end
$scope module stack_name $end
$var reg 14 +" \cstack[0] [13:0] $end
$upscope $end
$upscope $end
$upscope $end
$scope module MNPU2_tb $end
$scope module dut $end
$scope module stack_name $end
$var reg 14 ," \cstack[1] [13:0] $end
$upscope $end
$upscope $end
$upscope $end
$scope module MNPU2_tb $end
$scope module dut $end
$scope module stack_name $end
$var reg 14 -" \cstack[2] [13:0] $end
$upscope $end
$upscope $end
$upscope $end
$scope module MNPU2_tb $end
$scope module dut $end
$scope module stack_name $end
$var reg 14 ." \cstack[3] [13:0] $end
$upscope $end
$upscope $end
$upscope $end
$scope module MNPU2_tb $end
$scope module dut $end
$scope module stack_name $end
$var reg 14 /" \cstack[4] [13:0] $end
$upscope $end
$upscope $end
$upscope $end
$scope module MNPU2_tb $end
$scope module dut $end
$scope module stack_name $end
$var reg 14 0" \cstack[5] [13:0] $end
$upscope $end
$upscope $end
$upscope $end
$scope module MNPU2_tb $end
$scope module dut $end
$scope module stack_name $end
$var reg 14 1" \cstack[6] [13:0] $end
$upscope $end
$upscope $end
$upscope $end
$scope module MNPU2_tb $end
$scope module dut $end
$scope module stack_name $end
$var reg 14 2" \cstack[7] [13:0] $end
$upscope $end
$upscope $end
$upscope $end
$enddefinitions $end
$comment Show the parameter values. $end
$dumpall
b1000 m
b1000 l
$end
#0
$dumpvars
b0 2"
b0 1"
b0 0"
b0 /"
b0 ."
b0 -"
b0 ,"
b0 +"
b0 *"
b0 )"
b0 ("
b0 '"
b0 &"
b0 %"
b0 $"
b0 #"
b0 ""
b0 !"
b0 ~
b0 }
b0 |
b0 {
b0 z
b0 y
b0 x
b0 w
b0 v
b0 u
b0 t
b0 s
b0 r
b0 q
b1000 p
b0 o
b0 n
b0 k
b0 j
b0 i
b0 h
b0 g
bx f
b0 e
bx d
b0 c
b0 b
b1000 a
0`
bx _
0^
b0 ]
bx \
bx [
b0 Z
b100000000 Y
b0 X
bx W
bx V
b0 U
b0 T
b0 S
b0 R
b0 Q
b0 P
xO
0N
bx M
b0 L
b0 K
b0 J
b1000 I
bx H
bx G
b0 F
b0 E
bx D
b0 C
b0 B
b0 A
0@
0?
0>
b0 =
b0 <
bx ;
bx :
bx 9
08
b0 7
bx 6
15
b0 4
03
b0 2
b0 1
b0 0
0/
bx .
bx -
0,
b0 +
b0 *
b0 )
bx (
b0 '
1&
0%
z$
1#
1"
1!
$end
#5
0"
0#
#10
b0 (
b0 6
b0 V
b0 _
b0 \
bz -
bz ;
bz G
b0 :
b0 D
b0 .
b0 9
b0 H
b0 M
b0 W
b0 [
b0 d
b0 f
b1 *
b1 Q
b1 c
b1 h
bx ]
b1000 J
1"
#15
0"
#20
b10 \
b1110 :
b1110 D
1`
b0 ]
1O
b10 *
b10 Q
b10 c
b10 h
b1110010 .
b1110010 9
b1110010 H
b1110010 M
b1110010 W
b1110010 [
b1110010 d
b1110010 f
b1000 J
1"
#25
0"
#30
0&
b1 \
b0 :
b0 D
b1 '
b1 C
b1 Z
1@
b1 E
b1 .
b1 9
b1 H
b1 M
b1 W
b1 [
b1 d
b1 f
0O
b11 *
b11 Q
b11 c
b11 h
1^
b10 ]
0`
b1000 J
1"
#35
0"
#40
b0 \
b1111 :
b1111 D
1&
b0 '
b0 C
b0 Z
b1 r
b1 ]
0^
1O
b100 *
b100 Q
b100 c
b100 h
b1111000 .
b1111000 9
b1111000 H
b1111000 M
b1111000 W
b1111000 [
b1111000 d
b1111000 f
b0 E
0@
b1000 J
1"
#45
0"
#50
0&
b100 \
b11100 :
b11100 D
b11100100 '
b11100100 C
b11100100 Z
1?
b1 E
b11100100 .
b11100100 9
b11100100 H
b11100100 M
b11100100 W
b11100100 [
b11100100 d
b11100100 f
b101 *
b101 Q
b101 c
b101 h
b0 ]
b1000 J
1"
#55
0"
#60
05
b11100100 A
b1 \
b0 :
b0 D
1&
b0 '
b0 C
b0 Z
b100 ]
b110 *
b110 Q
b110 c
b110 h
b1 .
b1 9
b1 H
b1 M
b1 W
b1 [
b1 d
b1 f
b0 E
b11100100 4
b11100100 =
b11100100 F
b11100100 T
b11100100 e
0?
b1000 J
1"
#65
0"
#70
b0 \
b10100 :
b10100 D
b11100100 '
b11100100 C
b11100100 Z
05
b11100100 A
b11100100 B
b10100000 .
b10100000 9
b10100000 H
b10100000 M
b10100000 W
b10100000 [
b10100000 d
b10100000 f
b111 *
b111 Q
b111 c
b111 h
1`
b1 ]
b1000 J
1"
#75
0"
#80
18
1>
b1 (
b1 6
b1 V
b1 _
b10 \
b101 :
b101 D
05
b11100011 A
b11100100 x
b11100100 q
b0 ]
0`
b1000 *
b1000 Q
b1000 c
b1000 h
b101010 .
b101010 9
b101010 H
b101010 M
b101010 W
b101010 [
b101010 d
b101010 f
b1000 J
1"
#85
0"
#90
08
b10101 :
b10101 D
b11100011 '
b11100011 C
b11100011 Z
0>
15
b0 A
1,
13
b11100011 B
b10101010 .
b10101010 9
b10101010 H
b10101010 M
b10101010 W
b10101010 [
b10101010 d
b10101010 f
0O
b1001 *
b1001 Q
b1001 c
b1001 h
b10 ]
b1000 J
1"
#95
0"
#100
b0 (
b0 6
b0 V
b0 _
b0 \
b0 :
b0 D
0&
b0 '
b0 C
b0 Z
1N
b1010 *
b1010 Q
b1010 c
b1010 h
b0 .
b0 9
b0 H
b0 M
b0 W
b0 [
b0 d
b0 f
b1 E
b0 B
b1000 J
1"
#105
0"
#110
1>
05
b11100100 A
1&
b101 :
b101 D
b0 E
b101000 .
b101000 9
b101000 H
b101000 M
b101000 W
b101000 [
b101000 d
b101000 f
1O
b1011 *
b1011 Q
b1011 c
b1011 h
0N
b0 ]
b1000 J
1"
#115
0"
#120
b111 \
b10101 :
b10101 D
b11100100 '
b11100100 C
b11100100 Z
0>
15
b0 A
b1100 *
b1100 Q
b1100 c
b1100 h
b10101111 .
b10101111 9
b10101111 H
b10101111 M
b10101111 W
b10101111 [
b10101111 d
b10101111 f
0,
b11100100 B
b1000 J
1"
#125
0"
#130
b1 (
b1 6
b1 V
b1 _
0&
b10 \
b10 :
b10 D
b0 '
b0 C
b0 Z
b0 B
b1 E
b10010 .
b10010 9
b10010 H
b10010 M
b10010 W
b10010 [
b10010 d
b10010 f
1N
0O
b1101 *
b1101 Q
b1101 c
b1101 h
b111 ]
b1000 J
1"
#135
0"
#140
08
b11100100 (
b11100100 6
b11100100 V
b11100100 _
b1 \
b1000 :
b1000 D
05
b1110010 A
1&
b10 ]
b1110 *
b1110 Q
b1110 c
b1110 h
0N
b1000001 .
b1000001 9
b1000001 H
b1000001 M
b1000001 W
b1000001 [
b1000001 d
b1000001 f
b0 E
b1000 J
1"
#145
0"
#150
b1 :
b1 D
b1110010 '
b1110010 C
b1110010 Z
05
b1110010 A
b1110010 (
b1110010 6
b1110010 V
b1110010 _
03
b1110010 B
b1001 .
b1001 9
b1001 H
b1001 M
b1001 W
b1001 [
b1001 d
b1001 f
1O
b1111 *
b1111 Q
b1111 c
b1111 h
1`
b1 ]
b1000 J
1"
#155
0"
#160
b0 (
b0 6
b0 V
b0 _
b0 \
b10100 :
b10100 D
05
b1110010 A
b1110010 q
0`
b10000 *
b10000 Q
b10000 c
b10000 h
b10100000 .
b10100000 9
b10100000 H
b10100000 M
b10100000 W
b10100000 [
b10100000 d
b10100000 f
b1110010 4
b1110010 =
b1110010 F
b1110010 T
b1110010 e
b1000 J
1"
#165
0"
